LICENSE
MANIFEST.in
README.md
setup.cfg
setup.py
Flask_DynamoDB_Viz.egg-info/PKG-INFO
Flask_DynamoDB_Viz.egg-info/SOURCES.txt
Flask_DynamoDB_Viz.egg-info/dependency_links.txt
Flask_DynamoDB_Viz.egg-info/not-zip-safe
Flask_DynamoDB_Viz.egg-info/requires.txt
Flask_DynamoDB_Viz.egg-info/top_level.txt
flask_dynamodb_viz/__init__.py
flask_dynamodb_viz/flask_ddb_viz.py
flask_dynamodb_viz/ui/list.html
flask_dynamodb_viz/ui/css/bootstrap.min.css
flask_dynamodb_viz/ui/css/style.css
flask_dynamodb_viz/ui/js/angular.min.js
flask_dynamodb_viz/ui/js/bootstrap.min.js
flask_dynamodb_viz/ui/js/jquery-1.11.2.min.js
flask_dynamodb_viz/ui/js/jquery-3.2.1.slim.min.js
flask_dynamodb_viz/ui/js/jquery-ui.min.js
flask_dynamodb_viz/ui/js/jquery.easy-autocomplete.min.js
flask_dynamodb_viz/ui/js/jquery.min.js
flask_dynamodb_viz/ui/js/popper.min.js